__init__.py
pam.py
pamylka-0.5.0.dist-info/METADATA
pamylka-0.5.0.dist-info/WHEEL
pamylka-0.5.0.dist-info/licenses/LICENSE
pamylka-0.5.0.dist-info/RECORD
