Metadata-Version: 2.1
Name: pamylka
Version: 0.5.0
Summary: Pamylka's python package
Project-URL: Homepage, https://github.com/pypa/pamylka
Project-URL: Issues, https://github.com/pypa/pamylka/issues
Author-email: Ahmed Elbehairy <ahmedelbehairy.72005@gmail.com>
License: Copyright (c) 2018 The Python Packaging Authority
License-File: LICENSE
Classifier: License :: OSI Approved :: MIT License
Classifier: Operating System :: OS Independent
Classifier: Programming Language :: Python :: 3
Requires-Python: >=3.10
Requires-Dist: arabic-reshaper==3.0.0
Requires-Dist: fake-useragent==1.4.0
Requires-Dist: pygame==2.5.2
Requires-Dist: pyodbc==5.0.1
Requires-Dist: selenium==4.16.0
